llpsdk/__init__.py
llpsdk/client.py
llpsdk/config.py
llpsdk/errors.py
llpsdk/handler.py
llpsdk/message.py
llpsdk/presence.py
llpsdk/py.typed
llpsdk-0.1.0.dist-info/METADATA
llpsdk-0.1.0.dist-info/WHEEL
llpsdk-0.1.0.dist-info/licenses/LICENSE
llpsdk-0.1.0.dist-info/RECORD
